{"data":{"assets":[{"type":"image","src":"./img/team1.jpg","unitDim":"px","height":0,"width":0},{"type":"image","src":"./img/team2.jpg","unitDim":"px","height":0,"width":0},{"type":"image","src":"./img/team3.jpg","unitDim":"px","height":0,"width":0},{"type":"image","src":"https://via.placeholder.com/350x250/78c5d6/fff","unitDim":"px","height":0,"width":0},{"type":"image","src":"https://via.placeholder.com/350x250/459ba8/fff","unitDim":"px","height":0,"width":0},{"type":"image","src":"https://via.placeholder.com/350x250/79c267/fff","unitDim":"px","height":0,"width":0},{"type":"image","src":"https://via.placeholder.com/350x250/c5d647/fff","unitDim":"px","height":0,"width":0},{"type":"image","src":"https://via.placeholder.com/350x250/f28c33/fff","unitDim":"px","height":0,"width":0},{"type":"image","src":"https://via.placeholder.com/350x250/e868a2/fff","unitDim":"px","height":0,"width":0},{"type":"image","src":"https://via.placeholder.com/350x250/cc4360/fff","unitDim":"px","height":0,"width":0},{"type":"image","src":"./img/work-desk.jpg","unitDim":"px","height":0,"width":0},{"type":"image","src":"./img/phone-app.png","unitDim":"px","height":0,"width":0},{"type":"image","src":"./img/bg-gr-v.png","unitDim":"px","height":0,"width":0}],"styles":[{"selectors":["#idgm"],"style":{"padding":"10px"}},{"selectors":[{"name":"gjs-row","private":1}],"style":{"display":"flex","justify-content":"flex-start","align-items":"stretch","flex-wrap":"nowrap","padding":"10px"}},{"selectors":[{"name":"gjs-row","private":1}],"style":{"flex-wrap":"wrap"},"mediaText":"(max-width: 768px)","atRuleType":"media"},{"selectors":[{"name":"gjs-cell","private":1}],"style":{"min-height":"75px","flex-grow":"1","flex-basis":"100%"}}],"pages":[{"frames":[{"component":{"type":"wrapper","stylable":["background","background-color","background-image","background-repeat","background-attachment","background-position","background-size"],"components":[{"type":"text","attributes":{"id":"idgm"},"components":[{"type":"textnode","content":"HRG"}]},{"name":"Row","droppable":".gjs-cell","resizable":{"tl":0,"tc":0,"tr":0,"cl":0,"cr":0,"bl":0,"br":0,"minDim":1},"classes":[{"name":"gjs-row","private":1}],"attributes":{"id":"ib8d"},"components":[{"name":"Cell","draggable":".gjs-row","stylable-require":["flex-basis"],"unstylable":["width"],"resizable":{"tl":0,"tc":0,"tr":0,"cl":0,"cr":1,"bl":0,"br":0,"minDim":1,"bc":0,"currentUnit":1,"step":0.2,"keyWidth":"flex-basis"},"classes":[{"name":"gjs-cell","private":1}],"attributes":{"id":"Foo"}}]}]},"id":"g3FYAEpiNQrLZNjb"}],"id":"1Un0EXyJa19yRb2w"}]}}